README.md
apps.py
setup.py
starlette_apps.egg-info/PKG-INFO
starlette_apps.egg-info/SOURCES.txt
starlette_apps.egg-info/dependency_links.txt
starlette_apps.egg-info/requires.txt
starlette_apps.egg-info/top_level.txt