Metadata-Version: 2.1
Name: starlette-apps
Version: 0.1.6
Summary: IoC for configuration of Starlette projects
Home-page: https://yourlabs.io/oss/starlette-apps
Author: James Pic
Author-email: jamespic@gmail.com
License: MIT
Keywords: django cli
Platform: UNKNOWN
Requires-Python: >=3
Provides-Extra: test
